getchar/__init__.py
getchar-2.0.0.dist-info/METADATA
getchar-2.0.0.dist-info/WHEEL
getchar-2.0.0.dist-info/top_level.txt
getchar-2.0.0.dist-info/RECORD
