Metadata-Version: 2.1
Name: getchar
Version: 2.0.0
Summary: Non-blocking readchar
Project-URL: Homepage, https://github.com/tovicheung/getchar
Keywords: io,readchar,stdin
Classifier: License :: OSI Approved :: MIT License
Classifier: Programming Language :: Python
Classifier: Programming Language :: Python :: 3
